{"classes":["KEYWORD"],"annotations":[["住宅建筑规范\r",{"entities":[[0,2,"KEYWORD"]]}],["中华人民共和国国家标准\r",{"entities":[]}],["住宅建筑规范\r",{"entities":[[0,4,"KEYWORD"]]}],["Residential building code\r",{"entities":[]}],["GB 50368-2005\r",{"entities":[]}],["主编部门：中华人民共和国建设部\r",{"entities":[]}],["批准部门：中华人民共和国建设部\r",{"entities":[]}],["施行日期：2006年3月1日\r",{"entities":[]}],null,null,null,null,null,null,null,null,null,null,null,null,null,null,null,null,null,null,null,null,null,null,null,null,null,null,null,["2.0.1  住宅建筑 residential building\r",{"entities":[[7,11,"KEYWORD"]]}],["供家庭居住使用的建筑（含与其他功能空间处于同一建筑中的住宅部分），简称住宅。\r",{"entities":[[35,37,"KEYWORD"]]}],["2.0.2  老年人住宅 house for the aged\r",{"entities":[[7,12,"KEYWORD"]]}],["供以老年人为核心的家庭居住使用的专用住宅。老年人住宅以套为单位，普通住宅楼栋中可设置若干套老年人住宅。\r",{"entities":[[21,26,"KEYWORD"]]}],["2.0.3  住宅单元 residential building unit\r",{"entities":[[9,11,"KEYWORD"]]}],["由多套住宅组成的建筑部分，该部分内的住户可通过共用楼梯和安全出口进行疏散。\r",{"entities":[[23,27,"KEYWORD"]]}],["2.0.4  套 dwelling space\r",{"entities":[]}],["由使用面积、居住空间组成的基本住宅单位。\r",{"entities":[[13,19,"KEYWORD"]]}],["2.0.5  无障碍通路 barrier-free passage\r",{"entities":[[7,12,"KEYWORD"]]}],["住宅外部的道路、绿地与公共服务设施等用地内的适合老年人、体弱者、残疾人、轮椅及童车等通行的交通设施。\r",{"entities":[]}],["2.0.6  绿地 green space\r",{"entities":[[7,9,"KEYWORD"]]}],["居住用地内公共绿地、宅旁绿地、公共服务设施所属绿地和道路绿地（即道路红线内的绿地）等各种形式绿地的总称，包括满足当地植树绿化覆土要求、方便居民出入的地下或半地下建筑的屋顶绿地，不包括其他屋顶、晒台的绿地及垂直绿化。\r",{"entities":[[26,30,"KEYWORD"]]}],["2.0.7  公共绿地 public green space\r",{"entities":[[7,11,"KEYWORD"]]}],["满足规定的日照要求、适合于安排游憩活动设施的、供居民共享的集中绿地。\r",{"entities":[[29,33,"KEYWORD"]]}],["2.0.8  绿地率 greening rate\r",{"entities":[[7,10,"KEYWORD"]]}],["居住用地内各类绿地面积的总和与用地面积的比率(％)。\r",{"entities":[[15,19,"KEYWORD"]]}],["2.0.9  入口平台 entrance platform\r",{"entities":[[7,11,"KEYWORD"]]}],["在台阶或坡道与建筑入口之间的水平地面。\r",{"entities":[[14,18,"KEYWORD"]]}],["2.0.10  无障碍住房 barrier-free residence\r",{"entities":[[8,13,"KEYWORD"]]}],["在住宅建筑中，设有乘轮椅者可进入和使用的住宅套房。\r",{"entities":[[20,24,"KEYWORD"]]}],["2.0.11  轮椅坡道 ramp for wheelchair\r",{"entities":[[8,12,"KEYWORD"]]}],["坡度、宽度及地面、扶手、高度等方面符合乘轮椅者通行要求的坡道。\r",{"entities":[]}],["2.0.12  地下室 basement\r",{"entities":[[8,11,"KEYWORD"]]}],["房间地面低于室外地平面的高度超过该房间净高的1/2者。\r",{"entities":[]}],["2.0.13  半地下室 semi-basement\r",{"entities":[[8,12,"KEYWORD"]]}],["房间地面低于室外地平面的高度超过该房间净高的1/3，且不超过1/2者。\r",{"entities":[]}],["2.0.14  设计使用年限 design working life\r",{"entities":[[8,14,"KEYWORD"]]}],["设计规定的结构或结构构件不需进行大修即可按其预定目的使用的时期。\r",{"entities":[]}],["2.0.15  作用 action\r",{"entities":[]}],["引起结构或结构构件产生内力和变形效应的原因。\r",{"entities":[]}],["2.0.16  非结构构件 non-structural element\r",{"entities":[[8,13,"KEYWORD"]]}],["连接于建筑结构的建筑构件、机电部件及其系统。\r",{"entities":[[10,12,"KEYWORD"]]}],["\r",{"entities":[]}],["3  基本规定\r",{"entities":[]}],["3.1  住宅基本要求\r",{"entities":[[5,7,"KEYWORD"]]}],["3.1.1    住宅建设应符合城市规划要求，保障居民的基本生活条件和环境，经济、合理、有效地使用土地和空间。\r",{"entities":[]}],["3.1.2  住宅选址时应考虑噪声、有害物质、电磁辐射和工程地质灾害、水文地质灾害等的不利影响。\r",{"entities":[[9,11,"KEYWORD"]]}],["3.1.3  住宅应具有与其居住人口规模相适应的公共服务设施、道路和公共绿地。\r",{"entities":[]}],null,null,["3.1.6  住宅应具有防火安全性能。\r",{"entities":[]}],["3.1.7  住宅应具备在紧急事态时人员从建筑中安全撤出的功能。\r",{"entities":[]}],["3.1.8  住宅应满足人体健康所需的通风、日照、自然采光和隔声要求。\r",{"entities":[]}],["3.1.9  住宅建设的选材应避免造成环境污染。\r",{"entities":[]}],["3.1.10  住宅必须进行节能设计，且住宅及其室内设备应能有效利用能源和水资源。\r",{"entities":[[14,18,"KEYWORD"]]}],["3.1.11  住宅建设应符合无障碍设计原则。\r",{"entities":[[8,12,"KEYWORD"]]}],["3.1.12  住宅应采取防止外窗玻璃、外墙装饰及其他附属设施等坠落或坠落伤人的措施。\r",{"entities":[[15,19,"KEYWORD"]]}],["\r",{"entities":[]}],["\r",{"entities":[]}],["3.2  许可原则\r",{"entities":[]}],["3.2.1  住宅建设必须采用质量合格并符合要求的材料与设备。\r",{"entities":[[7,11,"KEYWORD"]]}],["3.2.2  当住宅建设采用不符合工程建设强制性标准的新技术、新工艺、新材料时，必须经相关程序核准。\r",{"entities":[[8,12,"KEYWORD"]]}],["3.2.3  未经技术鉴定和设计认可，不得拆改结构构件和进行加层改造。\r",{"entities":[]}],["\r",{"entities":[]}],["3.3  既有住宅\r",{"entities":[[5,9,"KEYWORD"]]}],["3.3.1  既有住宅达到设计使用年限或遭遇重大灾害后，需要继续使用时，应委托具有相应资质的机构鉴定，并根据鉴定结论进行处理。\r",{"entities":[[13,19,"KEYWORD"]]}],["3.3.2  既有住宅进行改造、改建时，应综合考虑节能、防火、抗震的要求。\r",{"entities":[[13,15,"KEYWORD"]]}],["\r",{"entities":[]}],["4  外部环境\r",{"entities":[]}],["4.1  相邻关系\r",{"entities":[]}],["4.1.1  住宅间距，应以满足日照要求为基础，综合考虑采光、通风、消防、防灾、管线埋设、视觉卫生等要求确定。住宅日照标准应符合表4.1.1的规定；对于特定情况还应符合下列规定：\r",{"entities":[[16,20,"KEYWORD"]]}],["1  老年人住宅不应低于冬至日日照2h的标准；\r",{"entities":[[12,17,"KEYWORD"]]}],["2  旧区改建的项目内新建住宅日照标准可酌情降低，但不应低于大寒日日照1h的标准。\r",{"entities":[[30,35,"KEYWORD"]]}],["表4.1.1 住宅建筑日照标准\r",{"entities":[[11,15,"KEYWORD"]]}],["\r",{"entities":[]}],["4.1.2  住宅至道路边缘的最小距离，应符合表4.1.2的规定。\r",{"entities":[[9,19,"KEYWORD"]]}],["表4.1.2住宅至道路边缘最小距离(m)\r",{"entities":[[9,17,"KEYWORD"]]}],["\r",{"entities":[]}],["\r",{"entities":[]}],["\r",{"entities":[]}],["4.1.3  住宅周边设置的各类管线不应影响住宅的安全，并应防止管线腐蚀、沉陷、振动及受重压。\r",{"entities":[[16,18,"KEYWORD"]]}],["\r",{"entities":[]}],["\r",{"entities":[]}],["4.2  公共服务设施\r",{"entities":[]}],["4.2.1  配套公共服务设施（配套公建）应包括：教育、医疗卫生、文化、体育、商业服务、金融邮电、社区服务、市政公用和行政管理等9类设施。\r",{"entities":[[9,15,"KEYWORD"]]}],["4.2.2  配套公建的项目与规模，必须与居住人口规模相对应，并应与住宅同步规划、同步建设、同期交付。\r",{"entities":[]}],["\r",{"entities":[]}],["4.3  道路交通\r",{"entities":[]}],["4.3.1  每个住宅单元至少应有一个出入口可以通达机动车。\r",{"entities":[[26,29,"KEYWORD"]]}],["4.3.2  道路设置应符合下列规定：\r",{"entities":[[7,11,"KEYWORD"]]}],["1  双车道道路的路面宽度不应小于6m；宅前路的路面宽度不应小于2.5m；\r",{"entities":[[3,8,"KEYWORD"]]}],["2  当尽端式道路的长度大于120m时，应在尽端设置不小于12m×12m的回车场地；\r",{"entities":[[37,41,"KEYWORD"]]}],["3  当主要道路坡度较大时，应设缓冲段与城市道路相接；\r",{"entities":[[16,19,"KEYWORD"]]}],["4  在抗震设防地区，道路交通应考虑减灾、救灾的要求。\r",{"entities":[[4,10,"KEYWORD"]]}],["4.3.3  无障碍通路应贯通，并应符合下列规定：\r",{"entities":[]}],["1  坡道的坡度应符合表4.3.3的规定。\r",{"entities":[[3,8,"KEYWORD"]]}],["表4.3.3 坡道的坡度\r",{"entities":[]}],["\r",{"entities":[]}],["2  人行道在交叉路口、街坊路口、广场入口处应设缘石坡道，其坡面应平整，且不应光滑。坡度应小于1：20，坡宽应大于1.2m。\r",{"entities":[[24,28,"KEYWORD"]]}],["3  通行轮椅车的坡道宽度不应小于1.5m。\r",{"entities":[[9,13,"KEYWORD"]]}],["4.3.4  居住用地内应配套设置居民自行车、汽车的停车场地或停车库。\r",{"entities":[[26,30,"KEYWORD"]]}],["\r",{"entities":[]}],["4.4  室外环境\r",{"entities":[]}],["4.4.1  新区的绿地率不应低于30％ 。\r",{"entities":[[7,13,"KEYWORD"]]}],["4.4.2  公共绿地总指标不应少于1m2/人。\r",{"entities":[[7,11,"KEYWORD"]]}],["4.4.3  人工景观水体的补充水严禁使用自来水。无护栏水体的近岸2m范围内及园桥、汀步附近2m范围内，水深不应大于0.5m。\r",{"entities":[[7,13,"KEYWORD"]]}],["4.4.4  受噪声影响的住宅周边应采取防噪措施。\r",{"entities":[[20,24,"KEYWORD"]]}],["\r",{"entities":[]}],["4.5  竖 向\r",{"entities":[]}],["4.5.1  地面水的排水系统，应根据地形特点设计，地面排水坡度不应小于0.2％。\r",{"entities":[[28,32,"KEYWORD"]]}],["4.5.2  住宅用地的防护工程设置应符合下列规定：\r",{"entities":[[12,16,"KEYWORD"]]}],["1  台阶式用地的台阶之间应用护坡或挡土墙连接，相邻台地间高差大于1.5m时，应在挡土墙或坡比值大于0.5的护坡顶面加设安全防护设施；\r",{"entities":[[18,21,"KEYWORD"]]}],["2  土质护坡的坡比值不应大于0.5；\r",{"entities":[[3,7,"KEYWORD"]]}],["3  高度大于2m的挡土墙和护坡的上缘与住宅间水平距离不应小于3m，其下缘与住宅间的水平距离不应小于2m。\r",{"entities":[[42,46,"KEYWORD"]]}],["\r",{"entities":[]}],["5  建筑\r",{"entities":[]}],["5.1  套内空间\r",{"entities":[]}],["5.1.1  每套住宅应设卧室、起居室（厅）、厨房和卫生间等基本空间。\r",{"entities":[[7,11,"KEYWORD"]]}],["5.1.2  厨房应设置炉灶、洗涤池、案台、排油烟机等设施或预留位置。\r",{"entities":[]}],["5.1.3  卫生间不应直接布置在下层住户的卧室、起居室（厅）、厨房、餐厅的上层。卫生间地面和局部墙面应有防水构造。\r",{"entities":[[53,57,"KEYWORD"]]}],["5.1.4  卫生间应设置便器、洗浴器、洗面器等设施或预留位置；布置便器的卫生间的门不应直接开在厨房内。\r",{"entities":[[37,42,"KEYWORD"]]}],["5.1.5  外窗窗台距楼面、地面的净高低于0.90m时，应有防护设施。六层及六层以下住宅的阳台栏杆净高不应低于1.05m，七层及七层以上住宅的阳台栏杆净高不应低于1.10m。阳台栏杆应有防护措施。防护栏杆的垂直杆件间净距不应大于0.11m。\r",{"entities":[[48,52,"KEYWORD"]]}],["5.1.6  卧室、起居室（厅）的室内净高不应低于2.40m，局部净高不应低于2.10m，局部净高的面积不应大于室内使用面积的1/3。利用坡屋顶内空间作卧室、起居室（厅）时，其1/2使用面积的室内净高不应低于2.10m。\r",{"entities":[[17,21,"KEYWORD"]]}],["5.1.7  阳台地面构造应有排水措施。\r",{"entities":[[7,11,"KEYWORD"]]}],["\r",{"entities":[]}],["\r",{"entities":[]}],["5.2  公共部分\r",{"entities":[]}],["5.2.1  走廊和公共部位通道的净宽不应小于1.20m，局部净高不应低于2.00m。\r",{"entities":[[17,19,"KEYWORD"]]}],["5.2.2  外廊、内天井及上人屋面等临空处栏杆净高，六层及六层以下不应低于1.05m；七层及七层以上不应低于1.10m。栏杆应防止攀登，垂直杆件间净距不应大于0.11m。\r",{"entities":[[69,76,"KEYWORD"]]}],["5.2.3  楼梯梯段净宽不应小于1.10m。六层及六层以下住宅，一边设有栏杆的梯段净宽不应小于1.00m。楼梯踏步宽度不应小于0.26m，踏步高度不应大于0.175m。扶手高度不应小于0.90m。楼梯水平段栏杆长度大于0.50m时，其扶手高度不应小于1.05m。楼梯栏杆垂直杆件间净距不应大于0.11m。楼梯井净宽大于0.11m时，必须采取防止儿童攀滑的措施。\r",{"entities":[[9,13,"KEYWORD"]]}],["5.2.4  住宅与附建公共用房的出入口应分开布置。住宅的公共出入口位于阳台、外廊及开敞楼梯平台的下部时，应采取防止物体坠落伤人的安全措施。\r",{"entities":[[56,69,"KEYWORD"]]}],["5.2.5  七层以及七层以上的住宅或住户入口层楼面距室外设计地面的高度超过16m以上的住宅必须设置电梯。\r",{"entities":[[50,52,"KEYWORD"]]}],["5.2.6  住宅建筑中设有管理人员室时，应设管理人员使用的卫生间。\r",{"entities":[[14,19,"KEYWORD"]]}],["\r",{"entities":[]}],["5.3  无障碍要求\r",{"entities":[]}],["5.3.1  七层及七层以上的住宅，应对下列部位进行无障碍设计：\r",{"entities":[]}],["1  建筑入口；\r",{"entities":[[3,7,"KEYWORD"]]}],["2  入口平台；\r",{"entities":[[3,7,"KEYWORD"]]}],["3  候梯厅；\r",{"entities":[[3,6,"KEYWORD"]]}],["4  公共走道；\r",{"entities":[[3,7,"KEYWORD"]]}],["5  无障碍住房。\r",{"entities":[[2,8,"KEYWORD"]]}],["5.3.2  建筑入口及入口平台的无障碍设计应符合下列规定：\r",{"entities":[]}],["1  建筑入口设台阶时，应设轮椅坡道和扶手；\r",{"entities":[]}],["2  坡道的坡度应符合表5.3.2的规定；\r",{"entities":[[3,8,"KEYWORD"]]}],["表5.3.2 坡道的坡度\r",{"entities":[[7,12,"KEYWORD"]]}],["\r",{"entities":[]}],["3  供轮椅通行的门净宽不应小于0.80m；\r",{"entities":[[3,12,"KEYWORD"]]}],["4  供轮椅通行的推拉门和平开门，在门把手一侧的墙面，应留有不小于0.50m的墙面宽度；\r",{"entities":[[9,12,"KEYWORD"]]}],["5  供轮椅通行的门扇，应安装视线观察玻璃、横执把手和关门拉手，在门扇的下方应安装高0.35m的护门板；\r",{"entities":[[3,11,"KEYWORD"]]}],["6  门槛高度及门内外地面高差不应大于15mm，并应以斜坡过渡。\r",{"entities":[[3,7,"KEYWORD"]]}],["5.3.3  七层及七层以上住宅建筑入口平台宽度不应小于2.00m。\r",{"entities":[]}],["5.3.4  供轮椅通行的走道和通道净宽不应小于1.20m。\r",{"entities":[]}],["\r",{"entities":[]}],["5.4  地 下 室\r",{"entities":[]}],["5.4.1  住宅的卧室、起居室（厅）、厨房不应布置在地下室。当布置在半地下室时，必须采取采光、通风、日照、防潮、排水及安全防护措施。\r",{"entities":[[27,30,"KEYWORD"]]}],["5.4.2  住宅地下机动车库应符合下列规定：\r",{"entities":[[7,15,"KEYWORD"]]}],["1  库内坡道严禁将宽的单车道兼作双车道。\r",{"entities":[[17,20,"KEYWORD"]]}],["2  库内不应设置修理车位，并不应设置使用或存放易燃、易爆物品的房间。\r",{"entities":[[9,13,"KEYWORD"]]}],["3  库内车道净高不应低于2.20m。车位净高不应低于2.00m。\r",{"entities":[[5,9,"KEYWORD"]]}],["4  库内直通住宅单元的楼（电）梯间应设门，严禁利用楼（电）梯间进行自然通风。\r",{"entities":[]}],["5.4.3  住宅地下自行车库净高不应低于2.00m。\r",{"entities":[[9,17,"KEYWORD"]]}],["5.4.4  住宅地下室应采取有效防水措施。\r",{"entities":[[15,21,"KEYWORD"]]}],["\r",{"entities":[]}],["6  结构\r",{"entities":[]}],["6.1  一般规定\r",{"entities":[]}],["6.1.1  住宅结构的设计使用年限不应少于50年，其安全等级不应低于二级。\r",{"entities":[[14,18,"KEYWORD"]]}],["6.1.2  抗震设防烈度为6度及以上地区的住宅结构必须进行抗震设计，其抗震设防类别不应低于丙类。\r",{"entities":[[7,13,"KEYWORD"]]}],["6.1.3  住宅结构设计应取得合格的岩土工程勘察文件。对不利地段，应提出避开要求或采取有效措施；严禁在抗震危险地段建造住宅建筑。\r",{"entities":[[19,25,"KEYWORD"]]}],["6.1.4  住宅结构应能承受在正常建造和正常使用过程中可能发生的各种作用和环境影响。在结构设计使用年限内，住宅结构和结构构件必须满足安全性、适用性和耐久性要求。\r",{"entities":[[59,63,"KEYWORD"]]}],["6.1.5  住宅结构不应产生影响结构安全的裂缝。\r",{"entities":[[15,24,"KEYWORD"]]}],["6.1.6  邻近住宅的永久性边坡的设计使用年限，不应低于受其影响的住宅结构的设计使用年限。\r",{"entities":[[12,17,"KEYWORD"]]}],["\r",{"entities":[]}],["\r",{"entities":[]}],["6.2  材 料\r",{"entities":[]}],["6.2.1  住宅结构材料应具有规定的物理、力学性能和耐久性能，并应符合节约资源和保护环境的原则。\r",{"entities":[]}],["6.2.2  住宅结构材料的强度标准值应具有不低于95％的保证率；抗震设防地区的住宅，其结构用钢材应符合抗震性能要求。\r",{"entities":[[11,16,"KEYWORD"]]}],["6.2.3  住宅结构用混凝土的强度等级不应低于C20。\r",{"entities":[[16,20,"KEYWORD"]]}],["6.2.4  住宅结构用钢材应具有抗拉强度、屈服强度、伸长率和硫、磷含量的合格保证；对焊接钢结构用钢材，尚应具有碳含量、冷弯试验的合格保证。\r",{"entities":[[9,14,"KEYWORD"]]}],["6.2.5  住宅结构中承重砌体材料的强度应符合下列规定：\r",{"entities":[[12,18,"KEYWORD"]]}],["1  烧结普通砖、烧结多孔砖、蒸压灰砂砖、蒸压粉煤灰砖的强度等级不应低于MU10；\r",{"entities":[[28,32,"KEYWORD"]]}],["2  混凝土砌块的强度等级不应低于MU7.5；\r",{"entities":[[3,8,"KEYWORD"]]}],["3  砖砌体的砂浆强度等级，抗震设计时不应低于M5；非抗震设计时，对低于五层的住宅不应低于M2.5，对不低于五层的住宅不应低于M5；\r",{"entities":[[9,13,"KEYWORD"]]}],["4  砌块砌体的砂浆强度等级，抗震设计时不应低于Mb7.5；非抗震设计时不应低于Mb5。\r",{"entities":[[8,10,"KEYWORD"]]}],["6.2.6  木结构住宅中，承重木材的强度等级不应低于TC11（针叶树种）或TB11（阔叶树种），其设计指标应考虑含水率的不利影响；承重结构用胶的胶合强度不应低于木材顺纹抗剪强度和横纹抗拉强度。\r",{"entities":[[7,10,"KEYWORD"]]}],["\r",{"entities":[]}],["6.3  地基基础\r",{"entities":[[5,9,"KEYWORD"]]}],["6.3.1  住宅应根据岩土工程勘察文件，综合考虑主体结构类型、地域特点、抗震设防烈度和施工条件等因素，进行地基基础设计。\r",{"entities":[[54,58,"KEYWORD"]]}],["6.3.2  住宅的地基基础应满足承载力和稳定性要求，地基变形应保证住宅的结构安全和正常使用。\r",{"entities":[[10,14,"KEYWORD"]]}],["6.3.3  基坑开挖及其支护应保证其自身及其周边环境的安全。\r",{"entities":[[7,9,"KEYWORD"]]}],["6.3.4  桩基础和经处理后的地基应进行承载力检验。\r",{"entities":[[7,10,"KEYWORD"]]}],["\r",{"entities":[]}],["6.4  上部结构\r",{"entities":[[5,9,"KEYWORD"]]}],["6.4.1  住宅应避免因局部破坏而导致整个结构丧失承载能力和稳定性。抗震设防地区的住宅不应采用严重不规则的设计方案。\r",{"entities":[]}],["6.4.2  抗震设防地区的住宅，应进行结构、结构构件的抗震验算，并应根据结构材料、结构体系、房屋高度、抗震设防烈度、场地类别等因素，采取可靠的抗震措施。\r",{"entities":[[72,76,"KEYWORD"]]}],["6.4.3  住宅结构中，刚度和承载力有突变的部位，应采取可靠的加强措施。9度抗震设防的住宅，不得采用错层结构、连体结构和带转换层的结构。\r",{"entities":[[39,43,"KEYWORD"]]}]]}